{
    "Events": {
        "ND-SAND": {
            "2018": 0.0,
            "2019": 0.0,
            "2020": 0.0,
            "2021": 0.0,
            "2022": 0.0,
            "2023": 0.0,
            "2024": 0.0,
            "2025": 0.0,
            "2026": 0.0,
            "2027": 0.0,
            "2028": 0.0,
            "2029": 0.0,
            "2030": 0.0,
            "2031": 15.0,
            "2032": 15.0,
            "2033": 15.0,
            "2034": 15.0,
            "2035": 15.0,
            "2036": 15.0,
            "2037": 15.0,
            "2038": 15.0,
            "2039": 15.0,
            "2040": 15.0
        },
        "ND-LAr+TMS": {
            "2018": 0.0,
            "2019": 0.0,
            "2020": 0.0,
            "2021": 0.0,
            "2022": 0.0,
            "2023": 0.0,
            "2024": 0.0,
            "2025": 0.0,
            "2026": 0.0,
            "2027": 0.0,
            "2028": 0.0,
            "2029": 0.0,
            "2030": 0.0,
            "2031": 15.0,
            "2032": 15.0,
            "2033": 15.0,
            "2034": 15.0,
            "2035": 15.0,
            "2036": 15.0,
            "2037": 15.0,
            "2038": 15.0,
            "2039": 15.0,
            "2040": 15.0
        },
        "PDs": {
            "2018": 10.9,
            "2019": 19.9,
            "2020": 7.4,
            "2021": 8.5,
            "2022": 10.1,
            "2023": 10.1,
            "2024": 40.4,
            "2025": 40.4,
            "2026": 10.1,
            "2027": 0.0,
            "2028": 0.0,
            "2029": 0.0,
            "2030": 0.0,
            "2031": 0.0,
            "2032": 0.0,
            "2033": 0.0,
            "2034": 0.0,
            "2035": 0.0,
            "2036": 0.0,
            "2037": 0.0,
            "2038": 0.0,
            "2039": 0.0,
            "2040": 0.0
        },
        "FDs": {
            "2018": 0.0,
            "2019": 0.0,
            "2020": 0.0,
            "2021": 0.0,
            "2022": 0.0,
            "2023": 0.0,
            "2024": 0.0,
            "2025": 0.0,
            "2026": 0.0,
            "2027": 0.0,
            "2028": 0.5,
            "2029": 3.3000000000000003,
            "2030": 4.4,
            "2031": 4.4,
            "2032": 4.4,
            "2033": 4.4,
            "2034": 4.4,
            "2035": 8.8,
            "2036": 8.8,
            "2037": 8.8,
            "2038": 8.8,
            "2039": 8.8,
            "2040": 8.8
        },
        "Total": {
            "2018": 10.9,
            "2019": 19.9,
            "2020": 7.4,
            "2021": 8.5,
            "2022": 10.1,
            "2023": 10.1,
            "2024": 40.4,
            "2025": 40.4,
            "2026": 10.1,
            "2027": 0.0,
            "2028": 0.5,
            "2029": 3.3000000000000003,
            "2030": 4.4,
            "2031": 34.4,
            "2032": 34.4,
            "2033": 34.4,
            "2034": 34.4,
            "2035": 38.8,
            "2036": 38.8,
            "2037": 38.8,
            "2038": 38.8,
            "2039": 38.8,
            "2040": 38.8
        }
    },
    "Test": {
        "ND-SAND": {
            "2018": 0.0,
            "2019": 0.0,
            "2020": 0.0,
            "2021": 0.0,
            "2022": 0.3,
            "2023": 1.0,
            "2024": 1.0,
            "2025": 1.0,
            "2026": 1.0,
            "2027": 1.0,
            "2028": 1.0,
            "2029": 1.0,
            "2030": 1.0,
            "2031": 1.0,
            "2032": 0.5,
            "2033": 0.5,
            "2034": 0.5,
            "2035": 0.5,
            "2036": 0.5,
            "2037": 0.5,
            "2038": 0.5,
            "2039": 0.5,
            "2040": 0.5
        },
        "ND-LAr+TMS": {
            "2018": 0.0,
            "2019": 0.0,
            "2020": 0.0,
            "2021": 0.0,
            "2022": 0.3,
            "2023": 1.0,
            "2024": 1.0,
            "2025": 1.0,
            "2026": 1.0,
            "2027": 1.0,
            "2028": 1.0,
            "2029": 1.0,
            "2030": 1.0,
            "2031": 1.0,
            "2032": 0.5,
            "2033": 0.5,
            "2034": 0.5,
            "2035": 0.5,
            "2036": 0.5,
            "2037": 0.5,
            "2038": 0.5,
            "2039": 0.5,
            "2040": 0.5
        },
        "PDs": {
            "2018": 0.157,
            "2019": 0.642,
            "2020": 1.0,
            "2021": 0.231,
            "2022": 2.231,
            "2023": 2.231,
            "2024": 0.7,
            "2025": 1.5,
            "2026": 1.0,
            "2027": 0.0,
            "2028": 0.0,
            "2029": 0.0,
            "2030": 0.0,
            "2031": 0.0,
            "2032": 0.0,
            "2033": 0.0,
            "2034": 0.0,
            "2035": 0.0,
            "2036": 0.0,
            "2037": 0.0,
            "2038": 0.0,
            "2039": 0.0,
            "2040": 0.0
        },
        "FDs": {
            "2018": 0.0,
            "2019": 0.0,
            "2020": 0.0,
            "2021": 0.0,
            "2022": 0.0,
            "2023": 0.0,
            "2024": 0.0,
            "2025": 0.0,
            "2026": 1.0,
            "2027": 5.0,
            "2028": 10.100000000000001,
            "2029": 11.100000000000001,
            "2030": 12.100000000000001,
            "2031": 12.100000000000001,
            "2032": 12.100000000000001,
            "2033": 12.100000000000001,
            "2034": 12.100000000000001,
            "2035": 12.100000000000001,
            "2036": 12.100000000000001,
            "2037": 2.1,
            "2038": 2.1,
            "2039": 2.1,
            "2040": 2.1
        },
        "Total": {
            "2018": 0.157,
            "2019": 0.642,
            "2020": 1.0,
            "2021": 0.231,
            "2022": 2.831,
            "2023": 4.231,
            "2024": 2.7,
            "2025": 3.5,
            "2026": 4.0,
            "2027": 7.0,
            "2028": 12.100000000000001,
            "2029": 13.100000000000001,
            "2030": 14.100000000000001,
            "2031": 14.100000000000001,
            "2032": 13.100000000000001,
            "2033": 13.100000000000001,
            "2034": 13.100000000000001,
            "2035": 13.100000000000001,
            "2036": 13.100000000000001,
            "2037": 3.1,
            "2038": 3.1,
            "2039": 3.1,
            "2040": 3.1
        }
    },
    "Sim-Events": {
        "ND-SAND": {
            "2018": 0.0,
            "2019": 0.0,
            "2020": 0.0,
            "2021": 10.0,
            "2022": 10.0,
            "2023": 10.0,
            "2024": 10.0,
            "2025": 10.0,
            "2026": 10.0,
            "2027": 15.0,
            "2028": 15.0,
            "2029": 15.0,
            "2030": 15.0,
            "2031": 15.0,
            "2032": 15.0,
            "2033": 15.0,
            "2034": 15.0,
            "2035": 15.0,
            "2036": 15.0,
            "2037": 15.0,
            "2038": 15.0,
            "2039": 15.0,
            "2040": 15.0
        },
        "ND-LAr+TMS": {
            "2018": 0.0,
            "2019": 0.0,
            "2020": 0.0,
            "2021": 0.0,
            "2022": 1.0,
            "2023": 1.0,
            "2024": 1.0,
            "2025": 1.0,
            "2026": 5.0,
            "2027": 10.0,
            "2028": 15.0,
            "2029": 15.0,
            "2030": 15.0,
            "2031": 15.0,
            "2032": 15.0,
            "2033": 15.0,
            "2034": 15.0,
            "2035": 15.0,
            "2036": 15.0,
            "2037": 15.0,
            "2038": 15.0,
            "2039": 15.0,
            "2040": 15.0
        },
        "PDs": {
            "2018": 2.5,
            "2019": 10.0,
            "2020": 10.0,
            "2021": 15.0,
            "2022": 15.1,
            "2023": 10.1,
            "2024": 10.1,
            "2025": 10.1,
            "2026": 10.1,
            "2027": 10.1,
            "2028": 0.0,
            "2029": 0.0,
            "2030": 0.0,
            "2031": 0.0,
            "2032": 0.0,
            "2033": 0.0,
            "2034": 0.0,
            "2035": 0.0,
            "2036": 0.0,
            "2037": 0.0,
            "2038": 0.0,
            "2039": 0.0,
            "2040": 0.0
        },
        "FDs": {
            "2018": 0.0,
            "2019": 0.0,
            "2020": 0.0,
            "2021": 0.0,
            "2022": 5.1,
            "2023": 20.2,
            "2024": 20.2,
            "2025": 20.2,
            "2026": 20.2,
            "2027": 20.2,
            "2028": 20.2,
            "2029": 20.2,
            "2030": 20.2,
            "2031": 20.2,
            "2032": 20.2,
            "2033": 20.2,
            "2034": 20.2,
            "2035": 20.2,
            "2036": 20.2,
            "2037": 20.2,
            "2038": 20.2,
            "2039": 20.2,
            "2040": 20.2
        },
        "Total": {
            "2018": 2.5,
            "2019": 10.0,
            "2020": 10.0,
            "2021": 25.0,
            "2022": 31.200000000000003,
            "2023": 41.3,
            "2024": 41.3,
            "2025": 41.3,
            "2026": 45.3,
            "2027": 55.3,
            "2028": 50.2,
            "2029": 50.2,
            "2030": 50.2,
            "2031": 50.2,
            "2032": 50.2,
            "2033": 50.2,
            "2034": 50.2,
            "2035": 50.2,
            "2036": 50.2,
            "2037": 50.2,
            "2038": 50.2,
            "2039": 50.2,
            "2040": 50.2
        }
    },
    "Raw-Store": {
        "ND-SAND": {
            "2018": 0.0,
            "2019": 0.0,
            "2020": 0.0,
            "2021": 0.0,
            "2022": 0.0,
            "2023": 0.0,
            "2024": 0.0,
            "2025": 0.0,
            "2026": 0.0,
            "2027": 0.0,
            "2028": 0.0,
            "2029": 0.0,
            "2030": 0.0,
            "2031": 0.075,
            "2032": 0.075,
            "2033": 0.075,
            "2034": 0.075,
            "2035": 0.04333172845450168,
            "2036": 0.04333172845450168,
            "2037": 0.04333172845450168,
            "2038": 0.04333172845450168,
            "2039": 0.04333172845450168,
            "2040": 0.04333172845450168
        },
        "ND-LAr+TMS": {
            "2018": 0.0,
            "2019": 0.0,
            "2020": 0.0,
            "2021": 0.0,
            "2022": 0.0,
            "2023": 0.0,
            "2024": 0.0,
            "2025": 0.0,
            "2026": 0.0,
            "2027": 0.0,
            "2028": 0.0,
            "2029": 0.0,
            "2030": 0.0,
            "2031": 0.15,
            "2032": 0.15,
            "2033": 0.15,
            "2034": 0.15,
            "2035": 0.08666345690900336,
            "2036": 0.08666345690900336,
            "2037": 0.08666345690900336,
            "2038": 0.08666345690900336,
            "2039": 0.08666345690900336,
            "2040": 0.08666345690900336
        },
        "Total": {
            "2018": 0.763,
            "2019": 1.413,
            "2020": 0.554,
            "2021": 0.675,
            "2022": 1.2610000000000001,
            "2023": 1.2610000000000001,
            "2024": 5.0440000000000005,
            "2025": 5.0440000000000005,
            "2026": 1.2610000000000001,
            "2027": 0.0,
            "2028": 1.875,
            "2029": 17.05,
            "2030": 25.85,
            "2031": 26.075000000000003,
            "2032": 26.075000000000003,
            "2033": 26.075000000000003,
            "2034": 26.075000000000003,
            "2035": 30.0,
            "2036": 30.0,
            "2037": 30.0,
            "2038": 30.0,
            "2039": 30.0,
            "2040": 30.0
        },
        "PDs": {
            "2018": 0.763,
            "2019": 1.413,
            "2020": 0.554,
            "2021": 0.675,
            "2022": 1.2610000000000001,
            "2023": 1.2610000000000001,
            "2024": 5.0440000000000005,
            "2025": 5.0440000000000005,
            "2026": 1.2610000000000001,
            "2027": 0.0,
            "2028": 0.0,
            "2029": 0.0,
            "2030": 0.0,
            "2031": 0.0,
            "2032": 0.0,
            "2033": 0.0,
            "2034": 0.0,
            "2035": 0.0,
            "2036": 0.0,
            "2037": 0.0,
            "2038": 0.0,
            "2039": 0.0,
            "2040": 0.0
        },
        "FDs": {
            "2018": 0.0,
            "2019": 0.0,
            "2020": 0.0,
            "2021": 0.0,
            "2022": 0.0,
            "2023": 0.0,
            "2024": 0.0,
            "2025": 0.0,
            "2026": 0.0,
            "2027": 0.0,
            "2028": 1.875,
            "2029": 17.05,
            "2030": 25.85,
            "2031": 25.85,
            "2032": 25.85,
            "2033": 25.85,
            "2034": 25.85,
            "2035": 29.870004814636495,
            "2036": 29.870004814636495,
            "2037": 29.870004814636495,
            "2038": 29.870004814636495,
            "2039": 29.870004814636495,
            "2040": 29.870004814636495
        }
    },
    "Reco-Data-CPU": {
        "ND-SAND": {
            "2018": 0.0,
            "2019": 0.0,
            "2020": 0.0,
            "2021": 0.0,
            "2022": 0.0,
            "2023": 0.0,
            "2024": 0.0,
            "2025": 0.0,
            "2026": 0.0,
            "2027": 0.0,
            "2028": 0.0,
            "2029": 0.0,
            "2030": 0.0,
            "2031": 0.033,
            "2032": 0.066,
            "2033": 0.099,
            "2034": 0.132,
            "2035": 0.165,
            "2036": 0.198,
            "2037": 0.231,
            "2038": 0.264,
            "2039": 0.29700000000000004,
            "2040": 0.33
        },
        "ND-LAr+TMS": {
            "2018": 0.0,
            "2019": 0.0,
            "2020": 0.0,
            "2021": 0.0,
            "2022": 0.0,
            "2023": 0.0,
            "2024": 0.0,
            "2025": 0.0,
            "2026": 0.0,
            "2027": 0.0,
            "2028": 0.0,
            "2029": 0.0,
            "2030": 0.0,
            "2031": 11.4,
            "2032": 22.8,
            "2033": 34.2,
            "2034": 45.6,
            "2035": 57.0,
            "2036": 68.4,
            "2037": 79.8,
            "2038": 91.2,
            "2039": 102.6,
            "2040": 114.0
        },
        "Total": {
            "2018": 1.81703,
            "2019": 5.134359999999999,
            "2020": 6.367939999999999,
            "2021": 5.967859999999999,
            "2022": 4.334199999999999,
            "2023": 4.7842899999999995,
            "2024": 10.10202,
            "2025": 15.153029999999998,
            "2026": 15.153029999999998,
            "2027": 8.41835,
            "2028": 2.3086699999999998,
            "2029": 4.838,
            "2030": 10.514,
            "2031": 27.623,
            "2032": 44.732,
            "2033": 61.841,
            "2034": 78.95,
            "2035": 101.735,
            "2036": 124.52,
            "2037": 147.305,
            "2038": 170.09,
            "2039": 192.87499999999997,
            "2040": 215.65999999999997
        },
        "PDs": {
            "2018": 1.81703,
            "2019": 5.134359999999999,
            "2020": 6.367939999999999,
            "2021": 5.967859999999999,
            "2022": 4.334199999999999,
            "2023": 4.7842899999999995,
            "2024": 10.10202,
            "2025": 15.153029999999998,
            "2026": 15.153029999999998,
            "2027": 8.41835,
            "2028": 1.6836699999999998,
            "2029": 0.0,
            "2030": 0.0,
            "2031": 0.0,
            "2032": 0.0,
            "2033": 0.0,
            "2034": 0.0,
            "2035": 0.0,
            "2036": 0.0,
            "2037": 0.0,
            "2038": 0.0,
            "2039": 0.0,
            "2040": 0.0
        },
        "FDs": {
            "2018": 0.0,
            "2019": 0.0,
            "2020": 0.0,
            "2021": 0.0,
            "2022": 0.0,
            "2023": 0.0,
            "2024": 0.0,
            "2025": 0.0,
            "2026": 0.0,
            "2027": 0.0,
            "2028": 0.625,
            "2029": 4.838,
            "2030": 10.514,
            "2031": 16.19,
            "2032": 21.866,
            "2033": 27.542,
            "2034": 33.218,
            "2035": 44.57,
            "2036": 55.922,
            "2037": 67.274,
            "2038": 78.626,
            "2039": 89.97799999999998,
            "2040": 101.32999999999998
        }
    },
    "Sim-CPU": {
        "ND-SAND": {
            "2018": 0.0,
            "2019": 0.0,
            "2020": 0.0,
            "2021": 2.4,
            "2022": 2.4,
            "2023": 2.4,
            "2024": 2.4,
            "2025": 2.4,
            "2026": 2.4,
            "2027": 3.5999999999999996,
            "2028": 3.5999999999999996,
            "2029": 3.5999999999999996,
            "2030": 3.5999999999999996,
            "2031": 3.5999999999999996,
            "2032": 3.5999999999999996,
            "2033": 3.5999999999999996,
            "2034": 3.5999999999999996,
            "2035": 3.5999999999999996,
            "2036": 3.5999999999999996,
            "2037": 3.5999999999999996,
            "2038": 3.5999999999999996,
            "2039": 3.5999999999999996,
            "2040": 3.5999999999999996
        },
        "ND-LAr+TMS": {
            "2018": 0.0,
            "2019": 0.0,
            "2020": 0.0,
            "2021": 0.0,
            "2022": 4.6,
            "2023": 4.6,
            "2024": 4.6,
            "2025": 4.6,
            "2026": 23.0,
            "2027": 46.0,
            "2028": 69.0,
            "2029": 69.0,
            "2030": 69.0,
            "2031": 69.0,
            "2032": 69.0,
            "2033": 69.0,
            "2034": 69.0,
            "2035": 69.0,
            "2036": 69.0,
            "2037": 69.0,
            "2038": 69.0,
            "2039": 69.0,
            "2040": 69.0
        },
        "Total": {
            "2018": 1.875,
            "2019": 7.5,
            "2020": 7.5,
            "2021": 13.65,
            "2022": 18.988,
            "2023": 16.701,
            "2024": 16.701,
            "2025": 16.701,
            "2026": 35.10099999999999,
            "2027": 59.300999999999995,
            "2028": 74.726,
            "2029": 74.726,
            "2030": 74.726,
            "2031": 74.726,
            "2032": 74.726,
            "2033": 74.726,
            "2034": 74.726,
            "2035": 74.726,
            "2036": 74.726,
            "2037": 74.726,
            "2038": 74.726,
            "2039": 74.726,
            "2040": 74.726
        },
        "PDs": {
            "2018": 1.875,
            "2019": 7.5,
            "2020": 7.5,
            "2021": 11.25,
            "2022": 11.325,
            "2023": 7.574999999999999,
            "2024": 7.574999999999999,
            "2025": 7.574999999999999,
            "2026": 7.574999999999999,
            "2027": 7.574999999999999,
            "2028": 0.0,
            "2029": 0.0,
            "2030": 0.0,
            "2031": 0.0,
            "2032": 0.0,
            "2033": 0.0,
            "2034": 0.0,
            "2035": 0.0,
            "2036": 0.0,
            "2037": 0.0,
            "2038": 0.0,
            "2039": 0.0,
            "2040": 0.0
        },
        "FDs": {
            "2018": 0.0,
            "2019": 0.0,
            "2020": 0.0,
            "2021": 0.0,
            "2022": 0.6629999999999999,
            "2023": 2.126,
            "2024": 2.126,
            "2025": 2.126,
            "2026": 2.126,
            "2027": 2.126,
            "2028": 2.126,
            "2029": 2.126,
            "2030": 2.126,
            "2031": 2.126,
            "2032": 2.126,
            "2033": 2.126,
            "2034": 2.126,
            "2035": 2.126,
            "2036": 2.126,
            "2037": 2.126,
            "2038": 2.126,
            "2039": 2.126,
            "2040": 2.126
        }
    },
    "Reco-Data-GPU": {
        "ND-SAND": {
            "2018": 0.0,
            "2019": 0.0,
            "2020": 0.0,
            "2021": 0.0,
            "2022": 0.0,
            "2023": 0.0,
            "2024": 0.0,
            "2025": 0.0,
            "2026": 0.0,
            "2027": 0.0,
            "2028": 0.0,
            "2029": 0.0,
            "2030": 0.0,
            "2031": 0.0,
            "2032": 0.0,
            "2033": 0.0,
            "2034": 0.0,
            "2035": 0.0,
            "2036": 0.0,
            "2037": 0.0,
            "2038": 0.0,
            "2039": 0.0,
            "2040": 0.0
        },
        "ND-LAr+TMS": {
            "2018": 0.0,
            "2019": 0.0,
            "2020": 0.0,
            "2021": 0.0,
            "2022": 0.0,
            "2023": 0.0,
            "2024": 0.0,
            "2025": 0.0,
            "2026": 0.0,
            "2027": 0.0,
            "2028": 0.0,
            "2029": 0.0,
            "2030": 0.0,
            "2031": 11.4,
            "2032": 22.8,
            "2033": 34.2,
            "2034": 45.6,
            "2035": 57.0,
            "2036": 68.4,
            "2037": 79.8,
            "2038": 91.2,
            "2039": 102.6,
            "2040": 114.0
        },
        "PDs": {
            "2018": 0.0,
            "2019": 0.0,
            "2020": 0.0,
            "2021": 0.0,
            "2022": 0.0,
            "2023": 0.0,
            "2024": 0.0,
            "2025": 0.0,
            "2026": 0.0,
            "2027": 0.0,
            "2028": 0.0,
            "2029": 0.0,
            "2030": 0.0,
            "2031": 0.0,
            "2032": 0.0,
            "2033": 0.0,
            "2034": 0.0,
            "2035": 0.0,
            "2036": 0.0,
            "2037": 0.0,
            "2038": 0.0,
            "2039": 0.0,
            "2040": 0.0
        },
        "FDs": {
            "2018": 0.0,
            "2019": 0.0,
            "2020": 0.0,
            "2021": 0.0,
            "2022": 0.0,
            "2023": 0.0,
            "2024": 0.0,
            "2025": 0.0,
            "2026": 0.0,
            "2027": 0.0,
            "2028": 0.0,
            "2029": 0.11000000000000001,
            "2030": 0.33000000000000007,
            "2031": 0.55,
            "2032": 0.77,
            "2033": 0.9900000000000001,
            "2034": 1.2100000000000002,
            "2035": 1.6500000000000001,
            "2036": 2.09,
            "2037": 2.53,
            "2038": 2.9699999999999998,
            "2039": 3.4099999999999997,
            "2040": 3.8499999999999996
        },
        "Total": {
            "2018": 0.0,
            "2019": 0.0,
            "2020": 0.0,
            "2021": 0.0,
            "2022": 0.0,
            "2023": 0.0,
            "2024": 0.0,
            "2025": 0.0,
            "2026": 0.0,
            "2027": 0.0,
            "2028": 0.0,
            "2029": 0.11000000000000001,
            "2030": 0.33000000000000007,
            "2031": 11.950000000000001,
            "2032": 23.57,
            "2033": 35.190000000000005,
            "2034": 46.81,
            "2035": 58.65,
            "2036": 70.49000000000001,
            "2037": 82.33,
            "2038": 94.17,
            "2039": 106.00999999999999,
            "2040": 117.85
        }
    },
    "Sim-GPU": {
        "ND-SAND": {
            "2018": 0.0,
            "2019": 0.0,
            "2020": 0.0,
            "2021": 0.0,
            "2022": 0.0,
            "2023": 0.0,
            "2024": 0.0,
            "2025": 0.0,
            "2026": 0.0,
            "2027": 0.0,
            "2028": 0.0,
            "2029": 0.0,
            "2030": 0.0,
            "2031": 0.0,
            "2032": 0.0,
            "2033": 0.0,
            "2034": 0.0,
            "2035": 0.0,
            "2036": 0.0,
            "2037": 0.0,
            "2038": 0.0,
            "2039": 0.0,
            "2040": 0.0
        },
        "ND-LAr+TMS": {
            "2018": 0.0,
            "2019": 0.0,
            "2020": 0.0,
            "2021": 0.0,
            "2022": 4.6,
            "2023": 4.6,
            "2024": 4.6,
            "2025": 4.6,
            "2026": 23.0,
            "2027": 46.0,
            "2028": 69.0,
            "2029": 69.0,
            "2030": 69.0,
            "2031": 69.0,
            "2032": 69.0,
            "2033": 69.0,
            "2034": 69.0,
            "2035": 69.0,
            "2036": 69.0,
            "2037": 69.0,
            "2038": 69.0,
            "2039": 69.0,
            "2040": 69.0
        },
        "PDs": {
            "2018": 0.0,
            "2019": 0.0,
            "2020": 0.0,
            "2021": 0.0,
            "2022": 0.0,
            "2023": 0.0,
            "2024": 0.0,
            "2025": 0.0,
            "2026": 0.0,
            "2027": 0.0,
            "2028": 0.0,
            "2029": 0.0,
            "2030": 0.0,
            "2031": 0.0,
            "2032": 0.0,
            "2033": 0.0,
            "2034": 0.0,
            "2035": 0.0,
            "2036": 0.0,
            "2037": 0.0,
            "2038": 0.0,
            "2039": 0.0,
            "2040": 0.0
        },
        "FDs": {
            "2018": 0.0,
            "2019": 0.0,
            "2020": 0.0,
            "2021": 0.0,
            "2022": 0.51,
            "2023": 1.02,
            "2024": 1.02,
            "2025": 1.02,
            "2026": 1.02,
            "2027": 1.02,
            "2028": 1.02,
            "2029": 1.02,
            "2030": 1.02,
            "2031": 1.02,
            "2032": 1.02,
            "2033": 1.02,
            "2034": 1.02,
            "2035": 1.02,
            "2036": 1.02,
            "2037": 1.02,
            "2038": 1.02,
            "2039": 1.02,
            "2040": 1.02
        },
        "Total": {
            "2018": 0.0,
            "2019": 0.0,
            "2020": 0.0,
            "2021": 0.0,
            "2022": 5.109999999999999,
            "2023": 5.619999999999999,
            "2024": 5.619999999999999,
            "2025": 5.619999999999999,
            "2026": 24.02,
            "2027": 47.02,
            "2028": 70.02,
            "2029": 70.02,
            "2030": 70.02,
            "2031": 70.02,
            "2032": 70.02,
            "2033": 70.02,
            "2034": 70.02,
            "2035": 70.02,
            "2036": 70.02,
            "2037": 70.02,
            "2038": 70.02,
            "2039": 70.02,
            "2040": 70.02
        }
    },
    "Reco-Data-Store": {
        "ND-SAND": {
            "2018": 0.0,
            "2019": 0.0,
            "2020": 0.0,
            "2021": 0.0,
            "2022": 0.0,
            "2023": 0.0,
            "2024": 0.0,
            "2025": 0.0,
            "2026": 0.0,
            "2027": 0.0,
            "2028": 0.0,
            "2029": 0.0,
            "2030": 0.0,
            "2031": 0.15,
            "2032": 0.3,
            "2033": 0.45,
            "2034": 0.6,
            "2035": 0.75,
            "2036": 0.9,
            "2037": 1.05,
            "2038": 1.2,
            "2039": 1.35,
            "2040": 1.5
        },
        "ND-LAr+TMS": {
            "2018": 0.0,
            "2019": 0.0,
            "2020": 0.0,
            "2021": 0.0,
            "2022": 0.0,
            "2023": 0.0,
            "2024": 0.0,
            "2025": 0.0,
            "2026": 0.0,
            "2027": 0.0,
            "2028": 0.0,
            "2029": 0.0,
            "2030": 0.0,
            "2031": 0.3,
            "2032": 0.6,
            "2033": 0.9,
            "2034": 1.2,
            "2035": 1.5,
            "2036": 1.8,
            "2037": 2.1,
            "2038": 2.4,
            "2039": 2.7,
            "2040": 3.0
        },
        "Total": {
            "2018": 0.3815,
            "2019": 1.078,
            "2020": 1.337,
            "2021": 1.2530000000000001,
            "2022": 0.8335,
            "2023": 0.8514999999999999,
            "2024": 1.662,
            "2025": 2.493,
            "2026": 2.493,
            "2027": 1.385,
            "2028": 0.28700000000000003,
            "2029": 0.076,
            "2030": 0.164,
            "2031": 0.702,
            "2032": 1.2399999999999998,
            "2033": 1.778,
            "2034": 2.316,
            "2035": 2.942,
            "2036": 3.568,
            "2037": 4.194000000000001,
            "2038": 4.819999999999999,
            "2039": 5.446000000000001,
            "2040": 6.072
        },
        "PDs": {
            "2018": 0.3815,
            "2019": 1.078,
            "2020": 1.337,
            "2021": 1.2530000000000001,
            "2022": 0.8335,
            "2023": 0.8514999999999999,
            "2024": 1.662,
            "2025": 2.493,
            "2026": 2.493,
            "2027": 1.385,
            "2028": 0.277,
            "2029": 0.0,
            "2030": 0.0,
            "2031": 0.0,
            "2032": 0.0,
            "2033": 0.0,
            "2034": 0.0,
            "2035": 0.0,
            "2036": 0.0,
            "2037": 0.0,
            "2038": 0.0,
            "2039": 0.0,
            "2040": 0.0
        },
        "FDs": {
            "2018": 0.0,
            "2019": 0.0,
            "2020": 0.0,
            "2021": 0.0,
            "2022": 0.0,
            "2023": 0.0,
            "2024": 0.0,
            "2025": 0.0,
            "2026": 0.0,
            "2027": 0.0,
            "2028": 0.01,
            "2029": 0.076,
            "2030": 0.164,
            "2031": 0.252,
            "2032": 0.33999999999999997,
            "2033": 0.42800000000000005,
            "2034": 0.516,
            "2035": 0.692,
            "2036": 0.868,
            "2037": 1.044,
            "2038": 1.2199999999999998,
            "2039": 1.396,
            "2040": 1.5719999999999998
        }
    },
    "Sim-Store": {
        "ND-SAND": {
            "2018": 0.0,
            "2019": 0.0,
            "2020": 0.0,
            "2021": 0.25,
            "2022": 0.25,
            "2023": 0.25,
            "2024": 0.25,
            "2025": 0.25,
            "2026": 0.25,
            "2027": 0.375,
            "2028": 0.375,
            "2029": 0.375,
            "2030": 0.375,
            "2031": 0.375,
            "2032": 0.375,
            "2033": 0.375,
            "2034": 0.375,
            "2035": 0.375,
            "2036": 0.375,
            "2037": 0.375,
            "2038": 0.375,
            "2039": 0.375,
            "2040": 0.375
        },
        "ND-LAr+TMS": {
            "2018": 0.0,
            "2019": 0.0,
            "2020": 0.0,
            "2021": 0.0,
            "2022": 0.05,
            "2023": 0.05,
            "2024": 0.05,
            "2025": 0.05,
            "2026": 0.25,
            "2027": 0.5,
            "2028": 0.75,
            "2029": 0.75,
            "2030": 0.75,
            "2031": 0.75,
            "2032": 0.75,
            "2033": 0.75,
            "2034": 0.75,
            "2035": 0.75,
            "2036": 0.75,
            "2037": 0.75,
            "2038": 0.75,
            "2039": 0.75,
            "2040": 0.75
        },
        "Total": {
            "2018": 0.55,
            "2019": 2.2,
            "2020": 2.2,
            "2021": 3.5500000000000003,
            "2022": 3.826,
            "2023": 3.33,
            "2024": 3.33,
            "2025": 3.33,
            "2026": 3.5300000000000002,
            "2027": 3.9050000000000002,
            "2028": 1.933,
            "2029": 1.933,
            "2030": 1.933,
            "2031": 1.933,
            "2032": 1.933,
            "2033": 1.933,
            "2034": 1.933,
            "2035": 1.933,
            "2036": 1.933,
            "2037": 1.933,
            "2038": 1.933,
            "2039": 1.933,
            "2040": 1.933
        },
        "PDs": {
            "2018": 0.55,
            "2019": 2.2,
            "2020": 2.2,
            "2021": 3.3000000000000003,
            "2022": 3.322,
            "2023": 2.2220000000000004,
            "2024": 2.2220000000000004,
            "2025": 2.2220000000000004,
            "2026": 2.2220000000000004,
            "2027": 2.2220000000000004,
            "2028": 0.0,
            "2029": 0.0,
            "2030": 0.0,
            "2031": 0.0,
            "2032": 0.0,
            "2033": 0.0,
            "2034": 0.0,
            "2035": 0.0,
            "2036": 0.0,
            "2037": 0.0,
            "2038": 0.0,
            "2039": 0.0,
            "2040": 0.0
        },
        "FDs": {
            "2018": 0.0,
            "2019": 0.0,
            "2020": 0.0,
            "2021": 0.0,
            "2022": 0.20400000000000001,
            "2023": 0.808,
            "2024": 0.808,
            "2025": 0.808,
            "2026": 0.808,
            "2027": 0.808,
            "2028": 0.808,
            "2029": 0.808,
            "2030": 0.808,
            "2031": 0.808,
            "2032": 0.808,
            "2033": 0.808,
            "2034": 0.808,
            "2035": 0.808,
            "2036": 0.808,
            "2037": 0.808,
            "2038": 0.808,
            "2039": 0.808,
            "2040": 0.808
        }
    },
    "Analysis-CPU": {
        "ND-SAND": {
            "2018": 0.0,
            "2019": 0.0,
            "2020": 0.0,
            "2021": 1.2,
            "2022": 1.2,
            "2023": 1.2,
            "2024": 1.2,
            "2025": 1.2,
            "2026": 1.2,
            "2027": 1.7999999999999998,
            "2028": 1.7999999999999998,
            "2029": 1.7999999999999998,
            "2030": 1.7999999999999998,
            "2031": 1.8164999999999998,
            "2032": 1.8329999999999997,
            "2033": 1.8495,
            "2034": 1.8659999999999999,
            "2035": 1.8824999999999998,
            "2036": 1.8989999999999998,
            "2037": 1.9154999999999998,
            "2038": 1.932,
            "2039": 1.9485,
            "2040": 1.9649999999999999
        },
        "ND-LAr+TMS": {
            "2018": 0.0,
            "2019": 0.0,
            "2020": 0.0,
            "2021": 0.0,
            "2022": 2.3,
            "2023": 2.3,
            "2024": 2.3,
            "2025": 2.3,
            "2026": 11.5,
            "2027": 23.0,
            "2028": 34.5,
            "2029": 34.5,
            "2030": 34.5,
            "2031": 40.2,
            "2032": 45.9,
            "2033": 51.6,
            "2034": 57.3,
            "2035": 63.0,
            "2036": 68.7,
            "2037": 74.4,
            "2038": 80.1,
            "2039": 85.8,
            "2040": 91.5
        },
        "Total": {
            "2018": 1.846015,
            "2019": 6.317179999999999,
            "2020": 6.9339699999999995,
            "2021": 9.80893,
            "2022": 13.5361,
            "2023": 14.492645000000001,
            "2024": 15.984985,
            "2025": 16.635489999999997,
            "2026": 25.127014999999997,
            "2027": 33.859675,
            "2028": 42.304835,
            "2029": 44.411334999999994,
            "2030": 43.461835,
            "2031": 51.1745,
            "2032": 59.729,
            "2033": 68.2835,
            "2034": 76.838,
            "2035": 88.23049999999999,
            "2036": 99.623,
            "2037": 111.0155,
            "2038": 122.40799999999999,
            "2039": 133.8005,
            "2040": 145.19299999999998
        },
        "PDs": {
            "2018": 1.846015,
            "2019": 6.317179999999999,
            "2020": 6.9339699999999995,
            "2021": 8.60893,
            "2022": 9.7046,
            "2023": 9.929645,
            "2024": 11.421985,
            "2025": 12.072489999999998,
            "2026": 11.364014999999998,
            "2027": 7.996675,
            "2028": 4.629334999999999,
            "2029": 4.629334999999999,
            "2030": 0.8418349999999999,
            "2031": 0.0,
            "2032": 0.0,
            "2033": 0.0,
            "2034": 0.0,
            "2035": 0.0,
            "2036": 0.0,
            "2037": 0.0,
            "2038": 0.0,
            "2039": 0.0,
            "2040": 0.0
        },
        "FDs": {
            "2018": 0.0,
            "2019": 0.0,
            "2020": 0.0,
            "2021": 0.0,
            "2022": 0.33149999999999996,
            "2023": 1.063,
            "2024": 1.063,
            "2025": 1.063,
            "2026": 1.063,
            "2027": 1.063,
            "2028": 1.3755,
            "2029": 3.482,
            "2030": 6.32,
            "2031": 9.158000000000001,
            "2032": 11.996000000000002,
            "2033": 14.834000000000001,
            "2034": 17.672000000000004,
            "2035": 23.348,
            "2036": 29.024,
            "2037": 34.7,
            "2038": 40.376,
            "2039": 46.05199999999999,
            "2040": 51.727999999999994
        }
    },
    "Total-CPU": {
        "PDs": {
            "2018": 5.538045,
            "2019": 18.951539999999998,
            "2020": 20.80191,
            "2021": 25.82679,
            "2022": 25.363799999999998,
            "2023": 22.288935,
            "2024": 29.099005,
            "2025": 34.80051999999999,
            "2026": 34.092045,
            "2027": 23.990025,
            "2028": 6.313004999999999,
            "2029": 4.629334999999999,
            "2030": 0.8418349999999999,
            "2031": 0.0,
            "2032": 0.0,
            "2033": 0.0,
            "2034": 0.0,
            "2035": 0.0,
            "2036": 0.0,
            "2037": 0.0,
            "2038": 0.0,
            "2039": 0.0,
            "2040": 0.0
        },
        "FDs": {
            "2018": 0.0,
            "2019": 0.0,
            "2020": 0.0,
            "2021": 0.0,
            "2022": 0.9944999999999999,
            "2023": 3.189,
            "2024": 3.189,
            "2025": 3.189,
            "2026": 3.189,
            "2027": 3.189,
            "2028": 4.1265,
            "2029": 10.446000000000002,
            "2030": 18.96,
            "2031": 27.474000000000004,
            "2032": 35.988,
            "2033": 44.502,
            "2034": 53.016000000000005,
            "2035": 70.044,
            "2036": 87.072,
            "2037": 104.10000000000001,
            "2038": 121.12800000000001,
            "2039": 138.15599999999998,
            "2040": 155.18399999999997
        },
        "ND-SAND": {
            "2018": 0.0,
            "2019": 0.0,
            "2020": 0.0,
            "2021": 3.5999999999999996,
            "2022": 3.5999999999999996,
            "2023": 3.5999999999999996,
            "2024": 3.5999999999999996,
            "2025": 3.5999999999999996,
            "2026": 3.5999999999999996,
            "2027": 5.3999999999999995,
            "2028": 5.3999999999999995,
            "2029": 5.3999999999999995,
            "2030": 5.3999999999999995,
            "2031": 5.4495,
            "2032": 5.498999999999999,
            "2033": 5.5485,
            "2034": 5.598,
            "2035": 5.647499999999999,
            "2036": 5.696999999999999,
            "2037": 5.746499999999999,
            "2038": 5.795999999999999,
            "2039": 5.8454999999999995,
            "2040": 5.895
        },
        "ND-LAr+TMS": {
            "2018": 0.0,
            "2019": 0.0,
            "2020": 0.0,
            "2021": 0.0,
            "2022": 6.8999999999999995,
            "2023": 6.8999999999999995,
            "2024": 6.8999999999999995,
            "2025": 6.8999999999999995,
            "2026": 34.5,
            "2027": 69.0,
            "2028": 103.5,
            "2029": 103.5,
            "2030": 103.5,
            "2031": 120.60000000000001,
            "2032": 137.7,
            "2033": 154.8,
            "2034": 171.89999999999998,
            "2035": 189.0,
            "2036": 206.10000000000002,
            "2037": 223.20000000000002,
            "2038": 240.29999999999998,
            "2039": 257.4,
            "2040": 274.5
        },
        "Total": {
            "2018": 5.538045,
            "2019": 18.951539999999998,
            "2020": 20.80191,
            "2021": 29.426789999999997,
            "2022": 36.85829999999999,
            "2023": 35.977934999999995,
            "2024": 42.788005,
            "2025": 48.48951999999999,
            "2026": 75.381045,
            "2027": 101.579025,
            "2028": 119.339505,
            "2029": 123.975335,
            "2030": 128.701835,
            "2031": 153.5235,
            "2032": 179.18699999999998,
            "2033": 204.8505,
            "2034": 230.51399999999998,
            "2035": 264.6915,
            "2036": 298.869,
            "2037": 333.04650000000004,
            "2038": 367.224,
            "2039": 401.40149999999994,
            "2040": 435.57899999999995
        },
        "FNAL": {
            "2018": 2.215218,
            "2019": 7.580615999999999,
            "2020": 8.320764,
            "2021": 11.770716,
            "2022": 14.743319999999997,
            "2023": 14.391174,
            "2024": 17.115202,
            "2025": 19.395808,
            "2026": 30.152418,
            "2027": 40.63161,
            "2028": 47.73580200000001,
            "2029": 61.9876675,
            "2030": 64.3509175,
            "2031": 76.76175,
            "2032": 89.59349999999999,
            "2033": 102.42525,
            "2034": 115.25699999999999,
            "2035": 132.34575,
            "2036": 149.4345,
            "2037": 166.52325000000002,
            "2038": 183.612,
            "2039": 200.70074999999997,
            "2040": 217.78949999999998
        },
        "CERN": {
            "2018": 0.5538045,
            "2019": 1.8951539999999998,
            "2020": 2.080191,
            "2021": 2.942679,
            "2022": 3.6858299999999993,
            "2023": 3.5977935,
            "2024": 4.2788005,
            "2025": 4.848952,
            "2026": 7.5381045,
            "2027": 10.1579025,
            "2028": 11.933950500000002,
            "2029": 0.0,
            "2030": 0.0,
            "2031": 0.0,
            "2032": 0.0,
            "2033": 0.0,
            "2034": 0.0,
            "2035": 0.0,
            "2036": 0.0,
            "2037": 0.0,
            "2038": 0.0,
            "2039": 0.0,
            "2040": 0.0
        },
        "National": {
            "2018": 2.7690225,
            "2019": 9.475769999999999,
            "2020": 10.400955,
            "2021": 14.713394999999998,
            "2022": 18.429149999999996,
            "2023": 17.988967499999998,
            "2024": 21.3940025,
            "2025": 24.244759999999996,
            "2026": 37.6905225,
            "2027": 50.7895125,
            "2028": 59.6697525,
            "2029": 61.9876675,
            "2030": 64.3509175,
            "2031": 76.76175,
            "2032": 89.59349999999999,
            "2033": 102.42525,
            "2034": 115.25699999999999,
            "2035": 132.34575,
            "2036": 149.4345,
            "2037": 166.52325000000002,
            "2038": 183.612,
            "2039": 200.70074999999997,
            "2040": 217.78949999999998
        }
    },
    "Cores": {
        "PDs": {
            "2018": 903.1384540117418,
            "2019": 3090.59686888454,
            "2020": 3392.3532289628183,
            "2021": 4211.805283757339,
            "2022": 4136.301369863014,
            "2023": 3634.855675146771,
            "2024": 4745.434605348989,
            "2025": 5675.2315720808865,
            "2026": 5559.694227005871,
            "2027": 3912.267612524462,
            "2028": 1029.5181017612522,
            "2029": 754.9469993476843,
            "2030": 137.28555120678408,
            "2031": 0.0,
            "2032": 0.0,
            "2033": 0.0,
            "2034": 0.0,
            "2035": 0.0,
            "2036": 0.0,
            "2037": 0.0,
            "2038": 0.0,
            "2039": 0.0,
            "2040": 0.0
        },
        "FDs": {
            "2018": 0.0,
            "2019": 0.0,
            "2020": 0.0,
            "2021": 0.0,
            "2022": 162.1819960861057,
            "2023": 520.0587084148729,
            "2024": 520.0587084148729,
            "2025": 520.0587084148729,
            "2026": 520.0587084148729,
            "2027": 520.0587084148729,
            "2028": 672.9452054794522,
            "2029": 1703.5225048923685,
            "2030": 3091.9765166340517,
            "2031": 4480.430528375735,
            "2032": 5868.884540117417,
            "2033": 7257.338551859101,
            "2034": 8645.792563600784,
            "2035": 11422.70058708415,
            "2036": 14199.608610567517,
            "2037": 16976.516634050884,
            "2038": 19753.42465753425,
            "2039": 22530.332681017608,
            "2040": 25307.240704500975
        },
        "ND-SAND": {
            "2018": 0.0,
            "2019": 0.0,
            "2020": 0.0,
            "2021": 587.0841487279844,
            "2022": 587.0841487279844,
            "2023": 587.0841487279844,
            "2024": 587.0841487279844,
            "2025": 587.0841487279844,
            "2026": 587.0841487279844,
            "2027": 880.6262230919765,
            "2028": 880.6262230919765,
            "2029": 880.6262230919765,
            "2030": 880.6262230919765,
            "2031": 888.6986301369863,
            "2032": 896.7710371819959,
            "2033": 904.843444227006,
            "2034": 912.9158512720156,
            "2035": 920.9882583170254,
            "2036": 929.0606653620351,
            "2037": 937.1330724070449,
            "2038": 945.2054794520548,
            "2039": 953.2778864970645,
            "2040": 961.3502935420744
        },
        "ND-LAr+TMS": {
            "2018": 0.0,
            "2019": 0.0,
            "2020": 0.0,
            "2021": 0.0,
            "2022": 1125.2446183953032,
            "2023": 1125.2446183953032,
            "2024": 1125.2446183953032,
            "2025": 1125.2446183953032,
            "2026": 5626.223091976517,
            "2027": 11252.446183953034,
            "2028": 16878.66927592955,
            "2029": 16878.66927592955,
            "2030": 16878.66927592955,
            "2031": 19667.318982387478,
            "2032": 22455.9686888454,
            "2033": 25244.61839530333,
            "2034": 28033.26810176125,
            "2035": 30821.91780821918,
            "2036": 33610.56751467711,
            "2037": 36399.21722113503,
            "2038": 39187.86692759296,
            "2039": 41976.51663405088,
            "2040": 44765.166340508804
        },
        "Total": {
            "2018": 903.1384540117418,
            "2019": 3090.59686888454,
            "2020": 3392.3532289628183,
            "2021": 4798.889432485323,
            "2022": 6010.812133072406,
            "2023": 5867.243150684932,
            "2024": 6977.822080887149,
            "2025": 7907.619047619047,
            "2026": 12293.060176125246,
            "2027": 16565.398727984346,
            "2028": 19461.75880626223,
            "2029": 20217.765003261582,
            "2030": 20988.55756686236,
            "2031": 25036.448140900196,
            "2032": 29221.624266144812,
            "2033": 33406.800391389435,
            "2034": 37591.97651663405,
            "2035": 43165.60665362036,
            "2036": 48739.23679060666,
            "2037": 54312.86692759297,
            "2038": 59886.49706457926,
            "2039": 65460.12720156555,
            "2040": 71033.75733855186
        },
        "FNAL": {
            "2018": 361.25538160469677,
            "2019": 1236.2387475538162,
            "2020": 1356.9412915851274,
            "2021": 1919.5557729941293,
            "2022": 2404.3248532289626,
            "2023": 2346.8972602739727,
            "2024": 2791.1288323548597,
            "2025": 3163.047619047619,
            "2026": 4917.224070450098,
            "2027": 6626.159491193739,
            "2028": 7784.703522504893,
            "2029": 10108.882501630791,
            "2030": 10494.27878343118,
            "2031": 12518.224070450098,
            "2032": 14610.812133072406,
            "2033": 16703.400195694718,
            "2034": 18795.988258317026,
            "2035": 21582.80332681018,
            "2036": 24369.61839530333,
            "2037": 27156.433463796486,
            "2038": 29943.24853228963,
            "2039": 32730.063600782774,
            "2040": 35516.87866927593
        },
        "CERN": {
            "2018": 90.31384540117419,
            "2019": 309.05968688845405,
            "2020": 339.23532289628184,
            "2021": 479.8889432485323,
            "2022": 601.0812133072407,
            "2023": 586.7243150684932,
            "2024": 697.7822080887149,
            "2025": 790.7619047619047,
            "2026": 1229.3060176125246,
            "2027": 1656.5398727984348,
            "2028": 1946.1758806262233,
            "2029": 0.0,
            "2030": 0.0,
            "2031": 0.0,
            "2032": 0.0,
            "2033": 0.0,
            "2034": 0.0,
            "2035": 0.0,
            "2036": 0.0,
            "2037": 0.0,
            "2038": 0.0,
            "2039": 0.0,
            "2040": 0.0
        },
        "National": {
            "2018": 451.5692270058709,
            "2019": 1545.29843444227,
            "2020": 1696.1766144814092,
            "2021": 2399.4447162426613,
            "2022": 3005.406066536203,
            "2023": 2933.621575342466,
            "2024": 3488.9110404435746,
            "2025": 3953.8095238095234,
            "2026": 6146.530088062623,
            "2027": 8282.699363992173,
            "2028": 9730.879403131115,
            "2029": 10108.882501630791,
            "2030": 10494.27878343118,
            "2031": 12518.224070450098,
            "2032": 14610.812133072406,
            "2033": 16703.400195694718,
            "2034": 18795.988258317026,
            "2035": 21582.80332681018,
            "2036": 24369.61839530333,
            "2037": 27156.433463796486,
            "2038": 29943.24853228963,
            "2039": 32730.063600782774,
            "2040": 35516.87866927593
        }
    },
    "HS23": {
        "PDs": {
            "2018": 9.934522994129159,
            "2019": 33.99656555772994,
            "2020": 37.315885518591,
            "2021": 46.32985812133072,
            "2022": 45.499315068493146,
            "2023": 39.98341242661448,
            "2024": 52.199780658838876,
            "2025": 62.42754729288975,
            "2026": 61.156636497064575,
            "2027": 43.03494373776908,
            "2028": 11.324699119373774,
            "2029": 8.304416992824526,
            "2030": 1.5101410632746248,
            "2031": 0.0,
            "2032": 0.0,
            "2033": 0.0,
            "2034": 0.0,
            "2035": 0.0,
            "2036": 0.0,
            "2037": 0.0,
            "2038": 0.0,
            "2039": 0.0,
            "2040": 0.0
        },
        "FDs": {
            "2018": 0.0,
            "2019": 0.0,
            "2020": 0.0,
            "2021": 0.0,
            "2022": 1.7840019569471626,
            "2023": 5.720645792563601,
            "2024": 5.720645792563601,
            "2025": 5.720645792563601,
            "2026": 5.720645792563601,
            "2027": 5.720645792563601,
            "2028": 7.402397260273974,
            "2029": 18.73874755381605,
            "2030": 34.01174168297457,
            "2031": 49.28473581213308,
            "2032": 64.55772994129158,
            "2033": 79.8307240704501,
            "2034": 95.10371819960862,
            "2035": 125.64970645792563,
            "2036": 156.19569471624268,
            "2037": 186.74168297455972,
            "2038": 217.28767123287676,
            "2039": 247.83365949119366,
            "2040": 278.3796477495107
        },
        "ND-SAND": {
            "2018": 0.0,
            "2019": 0.0,
            "2020": 0.0,
            "2021": 6.457925636007828,
            "2022": 6.457925636007828,
            "2023": 6.457925636007828,
            "2024": 6.457925636007828,
            "2025": 6.457925636007828,
            "2026": 6.457925636007828,
            "2027": 9.686888454011742,
            "2028": 9.686888454011742,
            "2029": 9.686888454011742,
            "2030": 9.686888454011742,
            "2031": 9.775684931506849,
            "2032": 9.864481409001954,
            "2033": 9.953277886497066,
            "2034": 10.042074363992171,
            "2035": 10.130870841487278,
            "2036": 10.219667318982387,
            "2037": 10.308463796477493,
            "2038": 10.397260273972602,
            "2039": 10.486056751467709,
            "2040": 10.574853228962818
        },
        "ND-LAr+TMS": {
            "2018": 0.0,
            "2019": 0.0,
            "2020": 0.0,
            "2021": 0.0,
            "2022": 12.377690802348335,
            "2023": 12.377690802348335,
            "2024": 12.377690802348335,
            "2025": 12.377690802348335,
            "2026": 61.888454011741686,
            "2027": 123.77690802348337,
            "2028": 185.66536203522506,
            "2029": 185.66536203522506,
            "2030": 185.66536203522506,
            "2031": 216.34050880626225,
            "2032": 247.0156555772994,
            "2033": 277.6908023483366,
            "2034": 308.36594911937374,
            "2035": 339.04109589041093,
            "2036": 369.7162426614482,
            "2037": 400.39138943248537,
            "2038": 431.0665362035225,
            "2039": 461.74168297455964,
            "2040": 492.41682974559683
        },
        "Total": {
            "2018": 9.934522994129159,
            "2019": 33.99656555772994,
            "2020": 37.315885518591,
            "2021": 52.787783757338545,
            "2022": 66.11893346379647,
            "2023": 64.53967465753425,
            "2024": 76.75604288975863,
            "2025": 86.98380952380951,
            "2026": 135.2236619373777,
            "2027": 182.2193860078278,
            "2028": 214.07934686888453,
            "2029": 222.3954150358774,
            "2030": 230.87413323548594,
            "2031": 275.4009295499022,
            "2032": 321.4378669275929,
            "2033": 367.4748043052838,
            "2034": 413.51174168297456,
            "2035": 474.8216731898239,
            "2036": 536.1316046966732,
            "2037": 597.4415362035227,
            "2038": 658.7514677103718,
            "2039": 720.061399217221,
            "2040": 781.3713307240704
        },
        "FNAL": {
            "2018": 3.9738091976516636,
            "2019": 13.598626223091976,
            "2020": 14.926354207436402,
            "2021": 21.11511350293542,
            "2022": 26.447573385518588,
            "2023": 25.815869863013702,
            "2024": 30.702417155903454,
            "2025": 34.793523809523805,
            "2026": 54.08946477495108,
            "2027": 72.88775440313113,
            "2028": 85.63173874755381,
            "2029": 111.1977075179387,
            "2030": 115.43706661774297,
            "2031": 137.7004647749511,
            "2032": 160.71893346379645,
            "2033": 183.7374021526419,
            "2034": 206.75587084148728,
            "2035": 237.41083659491196,
            "2036": 268.0658023483366,
            "2037": 298.72076810176134,
            "2038": 329.3757338551859,
            "2039": 360.0306996086105,
            "2040": 390.6856653620352
        },
        "CERN": {
            "2018": 0.9934522994129159,
            "2019": 3.399656555772994,
            "2020": 3.7315885518591005,
            "2021": 5.278778375733855,
            "2022": 6.611893346379647,
            "2023": 6.453967465753426,
            "2024": 7.6756042889758636,
            "2025": 8.698380952380951,
            "2026": 13.52236619373777,
            "2027": 18.22193860078278,
            "2028": 21.407934686888453,
            "2029": 0.0,
            "2030": 0.0,
            "2031": 0.0,
            "2032": 0.0,
            "2033": 0.0,
            "2034": 0.0,
            "2035": 0.0,
            "2036": 0.0,
            "2037": 0.0,
            "2038": 0.0,
            "2039": 0.0,
            "2040": 0.0
        },
        "National": {
            "2018": 4.967261497064579,
            "2019": 16.99828277886497,
            "2020": 18.6579427592955,
            "2021": 26.393891878669272,
            "2022": 33.05946673189823,
            "2023": 32.269837328767125,
            "2024": 38.378021444879316,
            "2025": 43.491904761904756,
            "2026": 67.61183096868885,
            "2027": 91.1096930039139,
            "2028": 107.03967343444226,
            "2029": 111.1977075179387,
            "2030": 115.43706661774297,
            "2031": 137.7004647749511,
            "2032": 160.71893346379645,
            "2033": 183.7374021526419,
            "2034": 206.75587084148728,
            "2035": 237.41083659491196,
            "2036": 268.0658023483366,
            "2037": 298.72076810176134,
            "2038": 329.3757338551859,
            "2039": 360.0306996086105,
            "2040": 390.6856653620352
        }
    },
    "Wall": {
        "PDs": {
            "2018": 7.911492857142858,
            "2019": 27.07362857142857,
            "2020": 29.71701428571429,
            "2021": 36.89541428571429,
            "2022": 36.234,
            "2023": 31.841335714285716,
            "2024": 41.57000714285714,
            "2025": 49.71502857142856,
            "2026": 48.70292142857143,
            "2027": 34.27146428571429,
            "2028": 9.01857857142857,
            "2029": 6.613335714285713,
            "2030": 1.2026214285714285,
            "2031": 0.0,
            "2032": 0.0,
            "2033": 0.0,
            "2034": 0.0,
            "2035": 0.0,
            "2036": 0.0,
            "2037": 0.0,
            "2038": 0.0,
            "2039": 0.0,
            "2040": 0.0
        },
        "FDs": {
            "2018": 0.0,
            "2019": 0.0,
            "2020": 0.0,
            "2021": 0.0,
            "2022": 1.4207142857142858,
            "2023": 4.555714285714286,
            "2024": 4.555714285714286,
            "2025": 4.555714285714286,
            "2026": 4.555714285714286,
            "2027": 4.555714285714286,
            "2028": 5.8950000000000005,
            "2029": 14.922857142857145,
            "2030": 27.08571428571429,
            "2031": 39.24857142857144,
            "2032": 51.41142857142857,
            "2033": 63.57428571428572,
            "2034": 75.73714285714287,
            "2035": 100.06285714285714,
            "2036": 124.38857142857144,
            "2037": 148.71428571428572,
            "2038": 173.04000000000002,
            "2039": 197.36571428571426,
            "2040": 221.69142857142853
        },
        "ND-SAND": {
            "2018": 0.0,
            "2019": 0.0,
            "2020": 0.0,
            "2021": 5.142857142857142,
            "2022": 5.142857142857142,
            "2023": 5.142857142857142,
            "2024": 5.142857142857142,
            "2025": 5.142857142857142,
            "2026": 5.142857142857142,
            "2027": 7.714285714285714,
            "2028": 7.714285714285714,
            "2029": 7.714285714285714,
            "2030": 7.714285714285714,
            "2031": 7.785,
            "2032": 7.855714285714284,
            "2033": 7.926428571428572,
            "2034": 7.997142857142857,
            "2035": 8.067857142857141,
            "2036": 8.138571428571428,
            "2037": 8.209285714285715,
            "2038": 8.28,
            "2039": 8.350714285714286,
            "2040": 8.42142857142857
        },
        "ND-LAr+TMS": {
            "2018": 0.0,
            "2019": 0.0,
            "2020": 0.0,
            "2021": 0.0,
            "2022": 9.857142857142858,
            "2023": 9.857142857142858,
            "2024": 9.857142857142858,
            "2025": 9.857142857142858,
            "2026": 49.28571428571429,
            "2027": 98.57142857142858,
            "2028": 147.85714285714286,
            "2029": 147.85714285714286,
            "2030": 147.85714285714286,
            "2031": 172.2857142857143,
            "2032": 196.71428571428572,
            "2033": 221.14285714285717,
            "2034": 245.57142857142856,
            "2035": 270.0,
            "2036": 294.4285714285715,
            "2037": 318.8571428571429,
            "2038": 343.2857142857143,
            "2039": 367.7142857142857,
            "2040": 392.14285714285717
        },
        "Total": {
            "2018": 7.911492857142858,
            "2019": 27.07362857142857,
            "2020": 29.71701428571429,
            "2021": 42.03827142857143,
            "2022": 52.65471428571428,
            "2023": 51.39704999999999,
            "2024": 61.12572142857143,
            "2025": 69.27074285714285,
            "2026": 107.68720714285715,
            "2027": 145.11289285714287,
            "2028": 170.48500714285717,
            "2029": 177.10762142857143,
            "2030": 183.85976428571428,
            "2031": 219.31928571428574,
            "2032": 255.98142857142855,
            "2033": 292.6435714285715,
            "2034": 329.30571428571426,
            "2035": 378.13071428571436,
            "2036": 426.95571428571435,
            "2037": 475.7807142857144,
            "2038": 524.6057142857143,
            "2039": 573.4307142857142,
            "2040": 622.2557142857142
        },
        "FNAL": {
            "2018": 3.1645971428571436,
            "2019": 10.82945142857143,
            "2020": 11.886805714285716,
            "2021": 16.81530857142857,
            "2022": 21.06188571428571,
            "2023": 20.558819999999997,
            "2024": 24.450288571428572,
            "2025": 27.70829714285714,
            "2026": 43.07488285714286,
            "2027": 58.04515714285715,
            "2028": 68.19400285714288,
            "2029": 88.55381071428572,
            "2030": 91.92988214285714,
            "2031": 109.65964285714287,
            "2032": 127.99071428571428,
            "2033": 146.32178571428574,
            "2034": 164.65285714285713,
            "2035": 189.06535714285718,
            "2036": 213.47785714285718,
            "2037": 237.8903571428572,
            "2038": 262.30285714285714,
            "2039": 286.7153571428571,
            "2040": 311.1278571428571
        },
        "CERN": {
            "2018": 0.7911492857142859,
            "2019": 2.7073628571428574,
            "2020": 2.971701428571429,
            "2021": 4.2038271428571425,
            "2022": 5.265471428571428,
            "2023": 5.139704999999999,
            "2024": 6.112572142857143,
            "2025": 6.927074285714285,
            "2026": 10.768720714285715,
            "2027": 14.511289285714287,
            "2028": 17.04850071428572,
            "2029": 0.0,
            "2030": 0.0,
            "2031": 0.0,
            "2032": 0.0,
            "2033": 0.0,
            "2034": 0.0,
            "2035": 0.0,
            "2036": 0.0,
            "2037": 0.0,
            "2038": 0.0,
            "2039": 0.0,
            "2040": 0.0
        },
        "National": {
            "2018": 3.955746428571429,
            "2019": 13.536814285714286,
            "2020": 14.858507142857144,
            "2021": 21.019135714285714,
            "2022": 26.32735714285714,
            "2023": 25.698524999999997,
            "2024": 30.562860714285716,
            "2025": 34.635371428571425,
            "2026": 53.843603571428574,
            "2027": 72.55644642857143,
            "2028": 85.24250357142859,
            "2029": 88.55381071428572,
            "2030": 91.92988214285714,
            "2031": 109.65964285714287,
            "2032": 127.99071428571428,
            "2033": 146.32178571428574,
            "2034": 164.65285714285713,
            "2035": 189.06535714285718,
            "2036": 213.47785714285718,
            "2037": 237.8903571428572,
            "2038": 262.30285714285714,
            "2039": 286.7153571428571,
            "2040": 311.1278571428571
        }
    }
}